unpackqa/__init__.py
unpackqa/base.py
unpackqa/product_loader.py
unpackqa/unpack.py
unpackqa/version.py
unpackqa/product_files/Landsat.yaml
unpackqa/product_files/MODIS.yaml
unpackqa/product_files/Template.yaml
unpackqa/tools/__init__.py
unpackqa/tools/unpackbits.py
unpackqa/tools/validation.py
unpackqa-0.2.1.dist-info/LICENSE
unpackqa-0.2.1.dist-info/METADATA
unpackqa-0.2.1.dist-info/WHEEL
unpackqa-0.2.1.dist-info/top_level.txt
unpackqa-0.2.1.dist-info/RECORD
