Metadata-Version: 2.1
Name: unpackqa
Version: 0.2.1
Summary: QA bit unpacking for Landsat, MODIS, Sentinal, VIIRS, and more.
Home-page: https://github.com/sdtaylor/unpackqa
Author: Shawn Taylor
License: MIT
Platform: UNKNOWN
Requires-Python: >=3.6.0
License-File: LICENSE
Requires-Dist: numpy (>=1.17.0)
Requires-Dist: pyyaml
